swandask/__init__.py
swandask/__main__.py
swandask/_version.py
swandask/app.py
swandask-0.0.6.data/data/etc/jupyter/jupyter_notebook_config.d/dask_labextension.json
swandask-0.0.6.data/data/etc/jupyter/jupyter_server_config.d/dask_labextension.json
swandask-0.0.6.dist-info/METADATA
swandask-0.0.6.dist-info/WHEEL
swandask-0.0.6.dist-info/entry_points.txt
swandask-0.0.6.dist-info/top_level.txt
swandask-0.0.6.dist-info/RECORD
